geometry/__init__.py
geometry/exceptions.py
geometry/figures.py
geometry/tests/__init__.py
geometry/tests/test_figures.py
geometry_nylinary-0.0.5.dist-info/METADATA
geometry_nylinary-0.0.5.dist-info/WHEEL
geometry_nylinary-0.0.5.dist-info/licenses/LICENSE
geometry_nylinary-0.0.5.dist-info/RECORD
