Metadata-Version: 2.3
Name: geometry-nylinary
Version: 0.0.5
Summary: Пакет для работы с геометрическими фигурами.
Author-email: Nikita Sysoev <nylinary@gmail.com>
License-File: LICENSE
Classifier: License :: OSI Approved :: MIT License
Classifier: Operating System :: OS Independent
Classifier: Programming Language :: Python :: 3
Requires-Python: >=3.2.15
